sparsebm/__init__.py
sparsebm/_datatypes.py
sparsebm/_entry_point.py
sparsebm/_graph_generator.py
sparsebm/_lbm.py
sparsebm/_model_selection.py
sparsebm/_sbm.py
sparsebm/utils.py
sparsebm-1.6.7.dist-info/LICENSE
sparsebm-1.6.7.dist-info/METADATA
sparsebm-1.6.7.dist-info/WHEEL
sparsebm-1.6.7.dist-info/entry_points.txt
sparsebm-1.6.7.dist-info/top_level.txt
sparsebm-1.6.7.dist-info/RECORD
