Metadata-Version: 2.1
Name: sparsebm
Version: 1.6.7
Summary: An implementation of Stochastic Bloc model and Latent Block model efficient with sparse matrices
Author-email: Gabriel Frisch <gabriel.frisch@hds.utc.fr>, Jean-Benoist Leger <jbleger@hds.utc.fr>
Maintainer-email: Jean-Benoist Leger <jbleger@hds.utc.fr>
License: MIT License
Project-URL: Repository, https://gitlab.com/jbleger/sparsebm
Project-URL: Documentation, https://jbleger.gitlab.io/sparsebm
Keywords: datamining,graph,LBM,SBM,variationnal,sparse
Classifier: License :: OSI Approved :: MIT License
Classifier: Development Status :: 4 - Beta
Classifier: Programming Language :: Python
Classifier: Intended Audience :: Science/Research
Classifier: Topic :: Scientific/Engineering :: Artificial Intelligence
Classifier: Topic :: Scientific/Engineering :: Mathematics
Requires-Python: >=3.7
License-File: LICENSE
Requires-Dist: progressbar2
Requires-Dist: matplotlib
Requires-Dist: scipy
Requires-Dist: numpy
Requires-Dist: gputil
Requires-Dist: scikit-learn
Provides-Extra: build-doc
Requires-Dist: sphinx (<7) ; extra == 'build-doc'
Requires-Dist: sphinx-argparse ; extra == 'build-doc'
Requires-Dist: m2r2 ; extra == 'build-doc'
Requires-Dist: sphinx-rtd-theme ; extra == 'build-doc'
Requires-Dist: pandas ; extra == 'build-doc'
Provides-Extra: experiments
Requires-Dist: rpy2 ; extra == 'experiments'
Provides-Extra: gpu
Requires-Dist: cupy ; extra == 'gpu'
Provides-Extra: tests
Requires-Dist: pytest ; extra == 'tests'
